README.rst
jambel.py
setup.py
jambel.egg-info/PKG-INFO
jambel.egg-info/SOURCES.txt
jambel.egg-info/dependency_links.txt
jambel.egg-info/entry_points.txt
jambel.egg-info/top_level.txt